odoo9_addon_account_invoice_merge_purchase-9.0.1.0.0-py2.7-nspkg.pth
odoo_addons/account_invoice_merge_purchase/__openerp__.py
odoo_addons/account_invoice_merge_purchase/__init__.py
odoo_addons/account_invoice_merge_purchase/README.rst
odoo_addons/account_invoice_merge_purchase/models/account_invoice.py
odoo_addons/account_invoice_merge_purchase/models/__init__.py
odoo_addons/account_invoice_merge_purchase/i18n/ja.po
odoo_addons/account_invoice_merge_purchase/i18n/zh_CN.po
odoo_addons/account_invoice_merge_purchase/i18n/nb_NO.po
odoo_addons/account_invoice_merge_purchase/i18n/tr_TR.po
odoo_addons/account_invoice_merge_purchase/i18n/ru.po
odoo_addons/account_invoice_merge_purchase/i18n/pt.po
odoo_addons/account_invoice_merge_purchase/i18n/fr_CH.po
odoo_addons/account_invoice_merge_purchase/i18n/it.po
odoo_addons/account_invoice_merge_purchase/i18n/es.po
odoo_addons/account_invoice_merge_purchase/i18n/nl_BE.po
odoo_addons/account_invoice_merge_purchase/i18n/ar.po
odoo_addons/account_invoice_merge_purchase/i18n/lt.po
odoo_addons/account_invoice_merge_purchase/i18n/ro.po
odoo_addons/account_invoice_merge_purchase/i18n/tr.po
odoo_addons/account_invoice_merge_purchase/i18n/mk.po
odoo_addons/account_invoice_merge_purchase/i18n/hr.po
odoo_addons/account_invoice_merge_purchase/i18n/bg.po
odoo_addons/account_invoice_merge_purchase/i18n/es_EC.po
odoo_addons/account_invoice_merge_purchase/i18n/zh_TW.po
odoo_addons/account_invoice_merge_purchase/i18n/gl.po
odoo_addons/account_invoice_merge_purchase/i18n/ca.po
odoo_addons/account_invoice_merge_purchase/i18n/id.po
odoo_addons/account_invoice_merge_purchase/i18n/es_CR.po
odoo_addons/account_invoice_merge_purchase/i18n/sl.po
odoo_addons/account_invoice_merge_purchase/i18n/th.po
odoo_addons/account_invoice_merge_purchase/i18n/cs.po
odoo_addons/account_invoice_merge_purchase/i18n/pt_PT.po
odoo_addons/account_invoice_merge_purchase/i18n/sk_SK.po
odoo_addons/account_invoice_merge_purchase/i18n/et.po
odoo9_addon_account_invoice_merge_purchase-9.0.1.0.0.dist-info/top_level.txt
odoo9_addon_account_invoice_merge_purchase-9.0.1.0.0.dist-info/WHEEL
odoo9_addon_account_invoice_merge_purchase-9.0.1.0.0.dist-info/RECORD
odoo9_addon_account_invoice_merge_purchase-9.0.1.0.0.dist-info/metadata.json
odoo9_addon_account_invoice_merge_purchase-9.0.1.0.0.dist-info/DESCRIPTION.rst
odoo9_addon_account_invoice_merge_purchase-9.0.1.0.0.dist-info/METADATA
odoo9_addon_account_invoice_merge_purchase-9.0.1.0.0.dist-info/namespace_packages.txt
